mesh_sdk/__init__.py
mesh_sdk/async_client.py
mesh_sdk/client.py
mesh_sdk/exceptions.py
mesh_sdk/models.py
mesh_sdk/validation.py
mesh_sdk/integrations/__init__.py
mesh_sdk/integrations/langchain.py
ai_mesh_sdk-1.0.0.dist-info/METADATA
ai_mesh_sdk-1.0.0.dist-info/WHEEL
ai_mesh_sdk-1.0.0.dist-info/top_level.txt
ai_mesh_sdk-1.0.0.dist-info/RECORD
